{"nodes": [{"id": "c_users_hp_git_campusflex_oldcode_engine_gamepanel_java", "label": "GamePanel.java", "file_type": "code", "source_file": "C:\\Users\\HP\\git\\CampusFlex\\OldCode\\engine\\GamePanel.java", "source_location": "L1"}, {"id": "engine_gamepanel_gamepanel", "label": "GamePanel", "file_type": "code", "source_file": "C:\\Users\\HP\\git\\CampusFlex\\OldCode\\engine\\GamePanel.java", "source_location": "L18"}, {"id": "jpanel", "label": "JPanel", "file_type": "code", "source_file": "", "source_location": ""}, {"id": "runnable", "label": "Runnable", "file_type": "code", "source_file": "", "source_location": ""}, {"id": "engine_gamepanel_gamepanel_gamepanel", "label": ".GamePanel()", "file_type": "code", "source_file": "C:\\Users\\HP\\git\\CampusFlex\\OldCode\\engine\\GamePanel.java", "source_location": "L57"}, {"id": "engine_gamepanel_gamepanel_startgamethread", "label": ".startGameThread()", "file_type": "code", "source_file": "C:\\Users\\HP\\git\\CampusFlex\\OldCode\\engine\\GamePanel.java", "source_location": "L74"}, {"id": "engine_gamepanel_gamepanel_run", "label": ".run()", "file_type": "code", "source_file": "C:\\Users\\HP\\git\\CampusFlex\\OldCode\\engine\\GamePanel.java", "source_location": "L79"}, {"id": "engine_gamepanel_gamepanel_update", "label": ".update()", "file_type": "code", "source_file": "C:\\Users\\HP\\git\\CampusFlex\\OldCode\\engine\\GamePanel.java", "source_location": "L99"}, {"id": "engine_gamepanel_gamepanel_clearkeys", "label": ".clearKeys()", "file_type": "code", "source_file": "C:\\Users\\HP\\git\\CampusFlex\\OldCode\\engine\\GamePanel.java", "source_location": "L126"}, {"id": "engine_gamepanel_gamepanel_updatefasttravel", "label": ".updateFastTravel()", "file_type": "code", "source_file": "C:\\Users\\HP\\git\\CampusFlex\\OldCode\\engine\\GamePanel.java", "source_location": "L139"}, {"id": "engine_gamepanel_gamepanel_teleporttozone", "label": ".teleportToZone()", "file_type": "code", "source_file": "C:\\Users\\HP\\git\\CampusFlex\\OldCode\\engine\\GamePanel.java", "source_location": "L153"}, {"id": "engine_gamepanel_gamepanel_updatelivelocation", "label": ".updateLiveLocation()", "file_type": "code", "source_file": "C:\\Users\\HP\\git\\CampusFlex\\OldCode\\engine\\GamePanel.java", "source_location": "L181"}, {"id": "engine_gamepanel_gamepanel_checkzonetransitions", "label": ".checkZoneTransitions()", "file_type": "code", "source_file": "C:\\Users\\HP\\git\\CampusFlex\\OldCode\\engine\\GamePanel.java", "source_location": "L226"}, {"id": "engine_gamepanel_gamepanel_checkinteractions", "label": ".checkInteractions()", "file_type": "code", "source_file": "C:\\Users\\HP\\git\\CampusFlex\\OldCode\\engine\\GamePanel.java", "source_location": "L312"}, {"id": "engine_gamepanel_gamepanel_paintcomponent", "label": ".paintComponent()", "file_type": "code", "source_file": "C:\\Users\\HP\\git\\CampusFlex\\OldCode\\engine\\GamePanel.java", "source_location": "L325"}], "edges": [{"source": "c_users_hp_git_campusflex_oldcode_engine_gamepanel_java", "target": "color", "relation": "imports", "confidence": "EXTRACTED", "source_file": "C:\\Users\\HP\\git\\CampusFlex\\OldCode\\engine\\GamePanel.java", "source_location": "L3", "weight": 1.0}, {"source": "c_users_hp_git_campusflex_oldcode_engine_gamepanel_java", "target": "dimension", "relation": "imports", "confidence": "EXTRACTED", "source_file": "C:\\Users\\HP\\git\\CampusFlex\\OldCode\\engine\\GamePanel.java", "source_location": "L4", "weight": 1.0}, {"source": "c_users_hp_git_campusflex_oldcode_engine_gamepanel_java", "target": "graphics", "relation": "imports", "confidence": "EXTRACTED", "source_file": "C:\\Users\\HP\\git\\CampusFlex\\OldCode\\engine\\GamePanel.java", "source_location": "L5", "weight": 1.0}, {"source": "c_users_hp_git_campusflex_oldcode_engine_gamepanel_java", "target": "graphics2d", "relation": "imports", "confidence": "EXTRACTED", "source_file": "C:\\Users\\HP\\git\\CampusFlex\\OldCode\\engine\\GamePanel.java", "source_location": "L6", "weight": 1.0}, {"source": "c_users_hp_git_campusflex_oldcode_engine_gamepanel_java", "target": "jpanel", "relation": "imports", "confidence": "EXTRACTED", "source_file": "C:\\Users\\HP\\git\\CampusFlex\\OldCode\\engine\\GamePanel.java", "source_location": "L7", "weight": 1.0}, {"source": "c_users_hp_git_campusflex_oldcode_engine_gamepanel_java", "target": "player", "relation": "imports", "confidence": "EXTRACTED", "source_file": "C:\\Users\\HP\\git\\CampusFlex\\OldCode\\engine\\GamePanel.java", "source_location": "L8", "weight": 1.0}, {"source": "c_users_hp_git_campusflex_oldcode_engine_gamepanel_java", "target": "tilemanager", "relation": "imports", "confidence": "EXTRACTED", "source_file": "C:\\Users\\HP\\git\\CampusFlex\\OldCode\\engine\\GamePanel.java", "source_location": "L9", "weight": 1.0}, {"source": "c_users_hp_git_campusflex_oldcode_engine_gamepanel_java", "target": "zonetype", "relation": "imports", "confidence": "EXTRACTED", "source_file": "C:\\Users\\HP\\git\\CampusFlex\\OldCode\\engine\\GamePanel.java", "source_location": "L10", "weight": 1.0}, {"source": "c_users_hp_git_campusflex_oldcode_engine_gamepanel_java", "target": "ui", "relation": "imports", "confidence": "EXTRACTED", "source_file": "C:\\Users\\HP\\git\\CampusFlex\\OldCode\\engine\\GamePanel.java", "source_location": "L11", "weight": 1.0}, {"source": "c_users_hp_git_campusflex_oldcode_engine_gamepanel_java", "target": "collisionchecker", "relation": "imports", "confidence": "EXTRACTED", "source_file": "C:\\Users\\HP\\git\\CampusFlex\\OldCode\\engine\\GamePanel.java", "source_location": "L12", "weight": 1.0}, {"source": "c_users_hp_git_campusflex_oldcode_engine_gamepanel_java", "target": "objectmanager", "relation": "imports", "confidence": "EXTRACTED", "source_file": "C:\\Users\\HP\\git\\CampusFlex\\OldCode\\engine\\GamePanel.java", "source_location": "L13", "weight": 1.0}, {"source": "c_users_hp_git_campusflex_oldcode_engine_gamepanel_java", "target": "campusmap", "relation": "imports", "confidence": "EXTRACTED", "source_file": "C:\\Users\\HP\\git\\CampusFlex\\OldCode\\engine\\GamePanel.java", "source_location": "L14", "weight": 1.0}, {"source": "c_users_hp_git_campusflex_oldcode_engine_gamepanel_java", "target": "location", "relation": "imports", "confidence": "EXTRACTED", "source_file": "C:\\Users\\HP\\git\\CampusFlex\\OldCode\\engine\\GamePanel.java", "source_location": "L15", "weight": 1.0}, {"source": "c_users_hp_git_campusflex_oldcode_engine_gamepanel_java", "target": "zone", "relation": "imports", "confidence": "EXTRACTED", "source_file": "C:\\Users\\HP\\git\\CampusFlex\\OldCode\\engine\\GamePanel.java", "source_location": "L16", "weight": 1.0}, {"source": "c_users_hp_git_campusflex_oldcode_engine_gamepanel_java", "target": "engine_gamepanel_gamepanel", "relation": "contains", "confidence": "EXTRACTED", "source_file": "C:\\Users\\HP\\git\\CampusFlex\\OldCode\\engine\\GamePanel.java", "source_location": "L18", "weight": 1.0}, {"source": "engine_gamepanel_gamepanel", "target": "jpanel", "relation": "extends", "confidence": "EXTRACTED", "source_file": "C:\\Users\\HP\\git\\CampusFlex\\OldCode\\engine\\GamePanel.java", "source_location": "L18", "weight": 1.0}, {"source": "engine_gamepanel_gamepanel", "target": "runnable", "relation": "implements", "confidence": "EXTRACTED", "source_file": "C:\\Users\\HP\\git\\CampusFlex\\OldCode\\engine\\GamePanel.java", "source_location": "L18", "weight": 1.0}, {"source": "engine_gamepanel_gamepanel", "target": "engine_gamepanel_gamepanel_gamepanel", "relation": "method", "confidence": "EXTRACTED", "source_file": "C:\\Users\\HP\\git\\CampusFlex\\OldCode\\engine\\GamePanel.java", "source_location": "L57", "weight": 1.0}, {"source": "engine_gamepanel_gamepanel", "target": "engine_gamepanel_gamepanel_startgamethread", "relation": "method", "confidence": "EXTRACTED", "source_file": "C:\\Users\\HP\\git\\CampusFlex\\OldCode\\engine\\GamePanel.java", "source_location": "L74", "weight": 1.0}, {"source": "engine_gamepanel_gamepanel", "target": "engine_gamepanel_gamepanel_run", "relation": "method", "confidence": "EXTRACTED", "source_file": "C:\\Users\\HP\\git\\CampusFlex\\OldCode\\engine\\GamePanel.java", "source_location": "L79", "weight": 1.0}, {"source": "engine_gamepanel_gamepanel", "target": "engine_gamepanel_gamepanel_update", "relation": "method", "confidence": "EXTRACTED", "source_file": "C:\\Users\\HP\\git\\CampusFlex\\OldCode\\engine\\GamePanel.java", "source_location": "L99", "weight": 1.0}, {"source": "engine_gamepanel_gamepanel", "target": "engine_gamepanel_gamepanel_clearkeys", "relation": "method", "confidence": "EXTRACTED", "source_file": "C:\\Users\\HP\\git\\CampusFlex\\OldCode\\engine\\GamePanel.java", "source_location": "L126", "weight": 1.0}, {"source": "engine_gamepanel_gamepanel", "target": "engine_gamepanel_gamepanel_updatefasttravel", "relation": "method", "confidence": "EXTRACTED", "source_file": "C:\\Users\\HP\\git\\CampusFlex\\OldCode\\engine\\GamePanel.java", "source_location": "L139", "weight": 1.0}, {"source": "engine_gamepanel_gamepanel", "target": "engine_gamepanel_gamepanel_teleporttozone", "relation": "method", "confidence": "EXTRACTED", "source_file": "C:\\Users\\HP\\git\\CampusFlex\\OldCode\\engine\\GamePanel.java", "source_location": "L153", "weight": 1.0}, {"source": "engine_gamepanel_gamepanel", "target": "engine_gamepanel_gamepanel_updatelivelocation", "relation": "method", "confidence": "EXTRACTED", "source_file": "C:\\Users\\HP\\git\\CampusFlex\\OldCode\\engine\\GamePanel.java", "source_location": "L181", "weight": 1.0}, {"source": "engine_gamepanel_gamepanel", "target": "engine_gamepanel_gamepanel_checkzonetransitions", "relation": "method", "confidence": "EXTRACTED", "source_file": "C:\\Users\\HP\\git\\CampusFlex\\OldCode\\engine\\GamePanel.java", "source_location": "L226", "weight": 1.0}, {"source": "engine_gamepanel_gamepanel", "target": "engine_gamepanel_gamepanel_checkinteractions", "relation": "method", "confidence": "EXTRACTED", "source_file": "C:\\Users\\HP\\git\\CampusFlex\\OldCode\\engine\\GamePanel.java", "source_location": "L312", "weight": 1.0}, {"source": "engine_gamepanel_gamepanel", "target": "engine_gamepanel_gamepanel_paintcomponent", "relation": "method", "confidence": "EXTRACTED", "source_file": "C:\\Users\\HP\\git\\CampusFlex\\OldCode\\engine\\GamePanel.java", "source_location": "L325", "weight": 1.0}, {"source": "engine_gamepanel_gamepanel_run", "target": "engine_gamepanel_gamepanel_update", "relation": "calls", "confidence": "EXTRACTED", "source_file": "C:\\Users\\HP\\git\\CampusFlex\\OldCode\\engine\\GamePanel.java", "source_location": "L92", "weight": 1.0}, {"source": "engine_gamepanel_gamepanel_update", "target": "engine_gamepanel_gamepanel_checkzonetransitions", "relation": "calls", "confidence": "EXTRACTED", "source_file": "C:\\Users\\HP\\git\\CampusFlex\\OldCode\\engine\\GamePanel.java", "source_location": "L111", "weight": 1.0}, {"source": "engine_gamepanel_gamepanel_update", "target": "engine_gamepanel_gamepanel_checkinteractions", "relation": "calls", "confidence": "EXTRACTED", "source_file": "C:\\Users\\HP\\git\\CampusFlex\\OldCode\\engine\\GamePanel.java", "source_location": "L112", "weight": 1.0}, {"source": "engine_gamepanel_gamepanel_update", "target": "engine_gamepanel_gamepanel_updatelivelocation", "relation": "calls", "confidence": "EXTRACTED", "source_file": "C:\\Users\\HP\\git\\CampusFlex\\OldCode\\engine\\GamePanel.java", "source_location": "L113", "weight": 1.0}, {"source": "engine_gamepanel_gamepanel_update", "target": "engine_gamepanel_gamepanel_updatefasttravel", "relation": "calls", "confidence": "EXTRACTED", "source_file": "C:\\Users\\HP\\git\\CampusFlex\\OldCode\\engine\\GamePanel.java", "source_location": "L122", "weight": 1.0}, {"source": "engine_gamepanel_gamepanel_updatefasttravel", "target": "engine_gamepanel_gamepanel_clearkeys", "relation": "calls", "confidence": "EXTRACTED", "source_file": "C:\\Users\\HP\\git\\CampusFlex\\OldCode\\engine\\GamePanel.java", "source_location": "L142", "weight": 1.0}, {"source": "engine_gamepanel_gamepanel_updatefasttravel", "target": "engine_gamepanel_gamepanel_teleporttozone", "relation": "calls", "confidence": "EXTRACTED", "source_file": "C:\\Users\\HP\\git\\CampusFlex\\OldCode\\engine\\GamePanel.java", "source_location": "L147", "weight": 1.0}, {"source": "engine_gamepanel_gamepanel_teleporttozone", "target": "engine_gamepanel_gamepanel_clearkeys", "relation": "calls", "confidence": "EXTRACTED", "source_file": "C:\\Users\\HP\\git\\CampusFlex\\OldCode\\engine\\GamePanel.java", "source_location": "L178", "weight": 1.0}, {"source": "engine_gamepanel_gamepanel_checkzonetransitions", "target": "engine_gamepanel_gamepanel_clearkeys", "relation": "calls", "confidence": "EXTRACTED", "source_file": "C:\\Users\\HP\\git\\CampusFlex\\OldCode\\engine\\GamePanel.java", "source_location": "L261", "weight": 1.0}], "raw_calls": [{"caller_nid": "engine_gamepanel_gamepanel_gamepanel", "callee": "setPreferredSize", "is_member_call": false, "source_file": "C:\\Users\\HP\\git\\CampusFlex\\OldCode\\engine\\GamePanel.java", "source_location": "L58"}, {"caller_nid": "engine_gamepanel_gamepanel_gamepanel", "callee": "setBackground", "is_member_call": false, "source_file": "C:\\Users\\HP\\git\\CampusFlex\\OldCode\\engine\\GamePanel.java", "source_location": "L59"}, {"caller_nid": "engine_gamepanel_gamepanel_gamepanel", "callee": "setDoubleBuffered", "is_member_call": false, "source_file": "C:\\Users\\HP\\git\\CampusFlex\\OldCode\\engine\\GamePanel.java", "source_location": "L60"}, {"caller_nid": "engine_gamepanel_gamepanel_gamepanel", "callee": "addKeyListener", "is_member_call": false, "source_file": "C:\\Users\\HP\\git\\CampusFlex\\OldCode\\engine\\GamePanel.java", "source_location": "L61"}, {"caller_nid": "engine_gamepanel_gamepanel_gamepanel", "callee": "setFocusable", "is_member_call": false, "source_file": "C:\\Users\\HP\\git\\CampusFlex\\OldCode\\engine\\GamePanel.java", "source_location": "L62"}, {"caller_nid": "engine_gamepanel_gamepanel_gamepanel", "callee": "loadCafeteriaObjects", "is_member_call": false, "source_file": "C:\\Users\\HP\\git\\CampusFlex\\OldCode\\engine\\GamePanel.java", "source_location": "L66"}, {"caller_nid": "engine_gamepanel_gamepanel_gamepanel", "callee": "loadLibraryObjects", "is_member_call": false, "source_file": "C:\\Users\\HP\\git\\CampusFlex\\OldCode\\engine\\GamePanel.java", "source_location": "L68"}, {"caller_nid": "engine_gamepanel_gamepanel_startgamethread", "callee": "start", "is_member_call": false, "source_file": "C:\\Users\\HP\\git\\CampusFlex\\OldCode\\engine\\GamePanel.java", "source_location": "L76"}, {"caller_nid": "engine_gamepanel_gamepanel_run", "callee": "nanoTime", "is_member_call": false, "source_file": "C:\\Users\\HP\\git\\CampusFlex\\OldCode\\engine\\GamePanel.java", "source_location": "L83"}, {"caller_nid": "engine_gamepanel_gamepanel_run", "callee": "nanoTime", "is_member_call": false, "source_file": "C:\\Users\\HP\\git\\CampusFlex\\OldCode\\engine\\GamePanel.java", "source_location": "L87"}, {"caller_nid": "engine_gamepanel_gamepanel_run", "callee": "repaint", "is_member_call": false, "source_file": "C:\\Users\\HP\\git\\CampusFlex\\OldCode\\engine\\GamePanel.java", "source_location": "L93"}, {"caller_nid": "engine_gamepanel_gamepanel_update", "callee": "updateTitleScreen", "is_member_call": false, "source_file": "C:\\Users\\HP\\git\\CampusFlex\\OldCode\\engine\\GamePanel.java", "source_location": "L101"}, {"caller_nid": "engine_gamepanel_gamepanel_update", "callee": "updatePauseScreen", "is_member_call": false, "source_file": "C:\\Users\\HP\\git\\CampusFlex\\OldCode\\engine\\GamePanel.java", "source_location": "L116"}, {"caller_nid": "engine_gamepanel_gamepanel_update", "callee": "updateOptionsScreen", "is_member_call": false, "source_file": "C:\\Users\\HP\\git\\CampusFlex\\OldCode\\engine\\GamePanel.java", "source_location": "L118"}, {"caller_nid": "engine_gamepanel_gamepanel_update", "callee": "updateCafeMenu", "is_member_call": false, "source_file": "C:\\Users\\HP\\git\\CampusFlex\\OldCode\\engine\\GamePanel.java", "source_location": "L120"}, {"caller_nid": "engine_gamepanel_gamepanel_teleporttozone", "callee": "loadMap", "is_member_call": false, "source_file": "C:\\Users\\HP\\git\\CampusFlex\\OldCode\\engine\\GamePanel.java", "source_location": "L155"}, {"caller_nid": "engine_gamepanel_gamepanel_teleporttozone", "callee": "clearObjects", "is_member_call": false, "source_file": "C:\\Users\\HP\\git\\CampusFlex\\OldCode\\engine\\GamePanel.java", "source_location": "L156"}, {"caller_nid": "engine_gamepanel_gamepanel_teleporttozone", "callee": "loadCafeteriaObjects", "is_member_call": false, "source_file": "C:\\Users\\HP\\git\\CampusFlex\\OldCode\\engine\\GamePanel.java", "source_location": "L158"}, {"caller_nid": "engine_gamepanel_gamepanel_teleporttozone", "callee": "loadLibraryObjects", "is_member_call": false, "source_file": "C:\\Users\\HP\\git\\CampusFlex\\OldCode\\engine\\GamePanel.java", "source_location": "L159"}, {"caller_nid": "engine_gamepanel_gamepanel_teleporttozone", "callee": "loadClassroomObjects", "is_member_call": false, "source_file": "C:\\Users\\HP\\git\\CampusFlex\\OldCode\\engine\\GamePanel.java", "source_location": "L160"}, {"caller_nid": "engine_gamepanel_gamepanel_teleporttozone", "callee": "loadPrayerAreaObjects", "is_member_call": false, "source_file": "C:\\Users\\HP\\git\\CampusFlex\\OldCode\\engine\\GamePanel.java", "source_location": "L161"}, {"caller_nid": "engine_gamepanel_gamepanel_teleporttozone", "callee": "loadServerRoomObjects", "is_member_call": false, "source_file": "C:\\Users\\HP\\git\\CampusFlex\\OldCode\\engine\\GamePanel.java", "source_location": "L162"}, {"caller_nid": "engine_gamepanel_gamepanel_updatelivelocation", "callee": "abs", "is_member_call": false, "source_file": "C:\\Users\\HP\\git\\CampusFlex\\OldCode\\engine\\GamePanel.java", "source_location": "L189"}, {"caller_nid": "engine_gamepanel_gamepanel_updatelivelocation", "callee": "abs", "is_member_call": false, "source_file": "C:\\Users\\HP\\git\\CampusFlex\\OldCode\\engine\\GamePanel.java", "source_location": "L189"}, {"caller_nid": "engine_gamepanel_gamepanel_updatelivelocation", "callee": "abs", "is_member_call": false, "source_file": "C:\\Users\\HP\\git\\CampusFlex\\OldCode\\engine\\GamePanel.java", "source_location": "L193"}, {"caller_nid": "engine_gamepanel_gamepanel_updatelivelocation", "callee": "abs", "is_member_call": false, "source_file": "C:\\Users\\HP\\git\\CampusFlex\\OldCode\\engine\\GamePanel.java", "source_location": "L193"}, {"caller_nid": "engine_gamepanel_gamepanel_updatelivelocation", "callee": "abs", "is_member_call": false, "source_file": "C:\\Users\\HP\\git\\CampusFlex\\OldCode\\engine\\GamePanel.java", "source_location": "L202"}, {"caller_nid": "engine_gamepanel_gamepanel_updatelivelocation", "callee": "getZone", "is_member_call": false, "source_file": "C:\\Users\\HP\\git\\CampusFlex\\OldCode\\engine\\GamePanel.java", "source_location": "L209"}, {"caller_nid": "engine_gamepanel_gamepanel_updatelivelocation", "callee": "getLocations", "is_member_call": false, "source_file": "C:\\Users\\HP\\git\\CampusFlex\\OldCode\\engine\\GamePanel.java", "source_location": "L212"}, {"caller_nid": "engine_gamepanel_gamepanel_updatelivelocation", "callee": "getX", "is_member_call": false, "source_file": "C:\\Users\\HP\\git\\CampusFlex\\OldCode\\engine\\GamePanel.java", "source_location": "L213"}, {"caller_nid": "engine_gamepanel_gamepanel_updatelivelocation", "callee": "getPosition", "is_member_call": false, "source_file": "C:\\Users\\HP\\git\\CampusFlex\\OldCode\\engine\\GamePanel.java", "source_location": "L213"}, {"caller_nid": "engine_gamepanel_gamepanel_updatelivelocation", "callee": "getY", "is_member_call": false, "source_file": "C:\\Users\\HP\\git\\CampusFlex\\OldCode\\engine\\GamePanel.java", "source_location": "L214"}, {"caller_nid": "engine_gamepanel_gamepanel_updatelivelocation", "callee": "getPosition", "is_member_call": false, "source_file": "C:\\Users\\HP\\git\\CampusFlex\\OldCode\\engine\\GamePanel.java", "source_location": "L214"}, {"caller_nid": "engine_gamepanel_gamepanel_updatelivelocation", "callee": "abs", "is_member_call": false, "source_file": "C:\\Users\\HP\\git\\CampusFlex\\OldCode\\engine\\GamePanel.java", "source_location": "L216"}, {"caller_nid": "engine_gamepanel_gamepanel_updatelivelocation", "callee": "abs", "is_member_call": false, "source_file": "C:\\Users\\HP\\git\\CampusFlex\\OldCode\\engine\\GamePanel.java", "source_location": "L217"}, {"caller_nid": "engine_gamepanel_gamepanel_updatelivelocation", "callee": "getName", "is_member_call": false, "source_file": "C:\\Users\\HP\\git\\CampusFlex\\OldCode\\engine\\GamePanel.java", "source_location": "L220"}, {"caller_nid": "engine_gamepanel_gamepanel_checkzonetransitions", "callee": "getZone", "is_member_call": false, "source_file": "C:\\Users\\HP\\git\\CampusFlex\\OldCode\\engine\\GamePanel.java", "source_location": "L231"}, {"caller_nid": "engine_gamepanel_gamepanel_checkzonetransitions", "callee": "getLocations", "is_member_call": false, "source_file": "C:\\Users\\HP\\git\\CampusFlex\\OldCode\\engine\\GamePanel.java", "source_location": "L233"}, {"caller_nid": "engine_gamepanel_gamepanel_checkzonetransitions", "callee": "getX", "is_member_call": false, "source_file": "C:\\Users\\HP\\git\\CampusFlex\\OldCode\\engine\\GamePanel.java", "source_location": "L234"}, {"caller_nid": "engine_gamepanel_gamepanel_checkzonetransitions", "callee": "getPosition", "is_member_call": false, "source_file": "C:\\Users\\HP\\git\\CampusFlex\\OldCode\\engine\\GamePanel.java", "source_location": "L234"}, {"caller_nid": "engine_gamepanel_gamepanel_checkzonetransitions", "callee": "getY", "is_member_call": false, "source_file": "C:\\Users\\HP\\git\\CampusFlex\\OldCode\\engine\\GamePanel.java", "source_location": "L235"}, {"caller_nid": "engine_gamepanel_gamepanel_checkzonetransitions", "callee": "getPosition", "is_member_call": false, "source_file": "C:\\Users\\HP\\git\\CampusFlex\\OldCode\\engine\\GamePanel.java", "source_location": "L235"}, {"caller_nid": "engine_gamepanel_gamepanel_checkzonetransitions", "callee": "abs", "is_member_call": false, "source_file": "C:\\Users\\HP\\git\\CampusFlex\\OldCode\\engine\\GamePanel.java", "source_location": "L238"}, {"caller_nid": "engine_gamepanel_gamepanel_checkzonetransitions", "callee": "abs", "is_member_call": false, "source_file": "C:\\Users\\HP\\git\\CampusFlex\\OldCode\\engine\\GamePanel.java", "source_location": "L238"}, {"caller_nid": "engine_gamepanel_gamepanel_checkzonetransitions", "callee": "equals", "is_member_call": false, "source_file": "C:\\Users\\HP\\git\\CampusFlex\\OldCode\\engine\\GamePanel.java", "source_location": "L242"}, {"caller_nid": "engine_gamepanel_gamepanel_checkzonetransitions", "callee": "getRequiredDirection", "is_member_call": false, "source_file": "C:\\Users\\HP\\git\\CampusFlex\\OldCode\\engine\\GamePanel.java", "source_location": "L242"}, {"caller_nid": "engine_gamepanel_gamepanel_checkzonetransitions", "callee": "equals", "is_member_call": false, "source_file": "C:\\Users\\HP\\git\\CampusFlex\\OldCode\\engine\\GamePanel.java", "source_location": "L243"}, {"caller_nid": "engine_gamepanel_gamepanel_checkzonetransitions", "callee": "getRequiredDirection", "is_member_call": false, "source_file": "C:\\Users\\HP\\git\\CampusFlex\\OldCode\\engine\\GamePanel.java", "source_location": "L243"}, {"caller_nid": "engine_gamepanel_gamepanel_checkzonetransitions", "callee": "equals", "is_member_call": false, "source_file": "C:\\Users\\HP\\git\\CampusFlex\\OldCode\\engine\\GamePanel.java", "source_location": "L244"}, {"caller_nid": "engine_gamepanel_gamepanel_checkzonetransitions", "callee": "getRequiredDirection", "is_member_call": false, "source_file": "C:\\Users\\HP\\git\\CampusFlex\\OldCode\\engine\\GamePanel.java", "source_location": "L244"}, {"caller_nid": "engine_gamepanel_gamepanel_checkzonetransitions", "callee": "equals", "is_member_call": false, "source_file": "C:\\Users\\HP\\git\\CampusFlex\\OldCode\\engine\\GamePanel.java", "source_location": "L245"}, {"caller_nid": "engine_gamepanel_gamepanel_checkzonetransitions", "callee": "getRequiredDirection", "is_member_call": false, "source_file": "C:\\Users\\HP\\git\\CampusFlex\\OldCode\\engine\\GamePanel.java", "source_location": "L245"}, {"caller_nid": "engine_gamepanel_gamepanel_checkzonetransitions", "callee": "getTargetZone", "is_member_call": false, "source_file": "C:\\Users\\HP\\git\\CampusFlex\\OldCode\\engine\\GamePanel.java", "source_location": "L248"}, {"caller_nid": "engine_gamepanel_gamepanel_checkzonetransitions", "callee": "loadMap", "is_member_call": false, "source_file": "C:\\Users\\HP\\git\\CampusFlex\\OldCode\\engine\\GamePanel.java", "source_location": "L249"}, {"caller_nid": "engine_gamepanel_gamepanel_checkzonetransitions", "callee": "clearObjects", "is_member_call": false, "source_file": "C:\\Users\\HP\\git\\CampusFlex\\OldCode\\engine\\GamePanel.java", "source_location": "L250"}, {"caller_nid": "engine_gamepanel_gamepanel_checkzonetransitions", "callee": "loadCafeteriaObjects", "is_member_call": false, "source_file": "C:\\Users\\HP\\git\\CampusFlex\\OldCode\\engine\\GamePanel.java", "source_location": "L252"}, {"caller_nid": "engine_gamepanel_gamepanel_checkzonetransitions", "callee": "loadLibraryObjects", "is_member_call": false, "source_file": "C:\\Users\\HP\\git\\CampusFlex\\OldCode\\engine\\GamePanel.java", "source_location": "L253"}, {"caller_nid": "engine_gamepanel_gamepanel_checkzonetransitions", "callee": "loadClassroomObjects", "is_member_call": false, "source_file": "C:\\Users\\HP\\git\\CampusFlex\\OldCode\\engine\\GamePanel.java", "source_location": "L254"}, {"caller_nid": "engine_gamepanel_gamepanel_checkzonetransitions", "callee": "loadPrayerAreaObjects", "is_member_call": false, "source_file": "C:\\Users\\HP\\git\\CampusFlex\\OldCode\\engine\\GamePanel.java", "source_location": "L255"}, {"caller_nid": "engine_gamepanel_gamepanel_checkzonetransitions", "callee": "loadServerRoomObjects", "is_member_call": false, "source_file": "C:\\Users\\HP\\git\\CampusFlex\\OldCode\\engine\\GamePanel.java", "source_location": "L256"}, {"caller_nid": "engine_gamepanel_gamepanel_checkzonetransitions", "callee": "loadAILabObjects", "is_member_call": false, "source_file": "C:\\Users\\HP\\git\\CampusFlex\\OldCode\\engine\\GamePanel.java", "source_location": "L257"}, {"caller_nid": "engine_gamepanel_gamepanel_checkzonetransitions", "callee": "getX", "is_member_call": false, "source_file": "C:\\Users\\HP\\git\\CampusFlex\\OldCode\\engine\\GamePanel.java", "source_location": "L259"}, {"caller_nid": "engine_gamepanel_gamepanel_checkzonetransitions", "callee": "getTargetSpawnPosition", "is_member_call": false, "source_file": "C:\\Users\\HP\\git\\CampusFlex\\OldCode\\engine\\GamePanel.java", "source_location": "L259"}, {"caller_nid": "engine_gamepanel_gamepanel_checkzonetransitions", "callee": "getY", "is_member_call": false, "source_file": "C:\\Users\\HP\\git\\CampusFlex\\OldCode\\engine\\GamePanel.java", "source_location": "L260"}, {"caller_nid": "engine_gamepanel_gamepanel_checkzonetransitions", "callee": "getTargetSpawnPosition", "is_member_call": false, "source_file": "C:\\Users\\HP\\git\\CampusFlex\\OldCode\\engine\\GamePanel.java", "source_location": "L260"}, {"caller_nid": "engine_gamepanel_gamepanel_checkzonetransitions", "callee": "abs", "is_member_call": false, "source_file": "C:\\Users\\HP\\git\\CampusFlex\\OldCode\\engine\\GamePanel.java", "source_location": "L277"}, {"caller_nid": "engine_gamepanel_gamepanel_checkzonetransitions", "callee": "loadMap", "is_member_call": false, "source_file": "C:\\Users\\HP\\git\\CampusFlex\\OldCode\\engine\\GamePanel.java", "source_location": "L286"}, {"caller_nid": "engine_gamepanel_gamepanel_checkzonetransitions", "callee": "loadAILabObjects", "is_member_call": false, "source_file": "C:\\Users\\HP\\git\\CampusFlex\\OldCode\\engine\\GamePanel.java", "source_location": "L287"}, {"caller_nid": "engine_gamepanel_gamepanel_checkzonetransitions", "callee": "loadMap", "is_member_call": false, "source_file": "C:\\Users\\HP\\git\\CampusFlex\\OldCode\\engine\\GamePanel.java", "source_location": "L290"}, {"caller_nid": "engine_gamepanel_gamepanel_checkzonetransitions", "callee": "loadClassroomObjects", "is_member_call": false, "source_file": "C:\\Users\\HP\\git\\CampusFlex\\OldCode\\engine\\GamePanel.java", "source_location": "L291"}, {"caller_nid": "engine_gamepanel_gamepanel_checkzonetransitions", "callee": "abs", "is_member_call": false, "source_file": "C:\\Users\\HP\\git\\CampusFlex\\OldCode\\engine\\GamePanel.java", "source_location": "L300"}, {"caller_nid": "engine_gamepanel_gamepanel_checkzonetransitions", "callee": "loadMap", "is_member_call": false, "source_file": "C:\\Users\\HP\\git\\CampusFlex\\OldCode\\engine\\GamePanel.java", "source_location": "L302"}, {"caller_nid": "engine_gamepanel_gamepanel_checkzonetransitions", "callee": "clearObjects", "is_member_call": false, "source_file": "C:\\Users\\HP\\git\\CampusFlex\\OldCode\\engine\\GamePanel.java", "source_location": "L303"}, {"caller_nid": "engine_gamepanel_gamepanel_paintcomponent", "callee": "draw", "is_member_call": false, "source_file": "C:\\Users\\HP\\git\\CampusFlex\\OldCode\\engine\\GamePanel.java", "source_location": "L331"}, {"caller_nid": "engine_gamepanel_gamepanel_paintcomponent", "callee": "draw", "is_member_call": false, "source_file": "C:\\Users\\HP\\git\\CampusFlex\\OldCode\\engine\\GamePanel.java", "source_location": "L333"}, {"caller_nid": "engine_gamepanel_gamepanel_paintcomponent", "callee": "draw", "is_member_call": false, "source_file": "C:\\Users\\HP\\git\\CampusFlex\\OldCode\\engine\\GamePanel.java", "source_location": "L334"}, {"caller_nid": "engine_gamepanel_gamepanel_paintcomponent", "callee": "draw", "is_member_call": false, "source_file": "C:\\Users\\HP\\git\\CampusFlex\\OldCode\\engine\\GamePanel.java", "source_location": "L335"}, {"caller_nid": "engine_gamepanel_gamepanel_paintcomponent", "callee": "draw", "is_member_call": false, "source_file": "C:\\Users\\HP\\git\\CampusFlex\\OldCode\\engine\\GamePanel.java", "source_location": "L336"}, {"caller_nid": "engine_gamepanel_gamepanel_paintcomponent", "callee": "dispose", "is_member_call": false, "source_file": "C:\\Users\\HP\\git\\CampusFlex\\OldCode\\engine\\GamePanel.java", "source_location": "L339"}]}